debby/__init__.py
debby/__main__.py
debby/artifacts.py
debby/checks/__init__.py
debby/checks/check_direct_join_to_source.py
debby/checks/check_duplicate_sources.py
debby/checks/check_marts_or_intermediate_dependent_on_source.py
debby/checks/check_model_descriptions.py
debby/checks/check_model_fanout.py
debby/checks/check_multiple_sources_joined.py
debby/checks/check_primary_key_tests.py
debby/checks/check_rejoining_upstream_concepts.py
debby/checks/check_root_models.py
debby/checks/check_source_descriptions.py
debby/checks/check_source_fanout.py
debby/checks/check_source_freshness_tests.py
debby/checks/check_source_table_descriptions.py
debby/checks/check_staging_dependent_on_staging.py
debby/checks/check_too_many_joins.py
debby/checks/check_unused_sources.py
debby/cli.py
debby/collector.py
debby/config.py
debby/core.py
debby/helpers.py
debby/runner.py
debby_cli-0.2.1.dist-info/METADATA
debby_cli-0.2.1.dist-info/WHEEL
debby_cli-0.2.1.dist-info/entry_points.txt
debby_cli-0.2.1.dist-info/RECORD
